agentsudo/__init__.py
agentsudo/cli.py
agentsudo/client.py
agentsudo/server.py
agentsudo/core/__init__.py
agentsudo/core/budget.py
agentsudo/core/policy_engine.py
agentsudo/integrations/__init__.py
agentsudo/integrations/langchain.py
agentsudo/integrations/phidata.py
agentsudo_core-0.1.0.dist-info/METADATA
agentsudo_core-0.1.0.dist-info/WHEEL
agentsudo_core-0.1.0.dist-info/entry_points.txt
agentsudo_core-0.1.0.dist-info/RECORD
