Metadata-Version: 2.4
Name: agentsudo-core
Version: 0.1.0
Summary: Zero Trust Security Middleware for AI Agents
Project-URL: Repository, https://github.com/IntellectMachines/agent-sudo-mvp
Author: IntellectMachines
License-Expression: MIT
Keywords: agents,ai,middleware,security,zero-trust
Requires-Python: >=3.10
Requires-Dist: click>=8.0.0
Requires-Dist: fastapi>=0.104.0
Requires-Dist: httpx>=0.25.0
Requires-Dist: pydantic>=2.0.0
Requires-Dist: pyyaml>=6.0
Requires-Dist: rich>=13.0.0
Requires-Dist: uvicorn>=0.24.0
Provides-Extra: dev
Requires-Dist: pytest-asyncio>=0.21.0; extra == 'dev'
Requires-Dist: pytest-cov>=4.0.0; extra == 'dev'
Requires-Dist: pytest>=7.0.0; extra == 'dev'
Requires-Dist: ruff>=0.1.0; extra == 'dev'
Provides-Extra: redis
Requires-Dist: redis>=5.0.0; extra == 'redis'
